{
  "alert": "BlissNatsConsumerLagWarning",
  "version": "v5",
  "alertType": "METRIC_BASED_ALERT",
  "ruleType": "threshold_rule",
  "evalWindow": "5m0s",
  "frequency": "1m0s",
  "condition": {
    "compositeQuery": {
      "queryType": "promql",
      "panelType": "graph",
      "promQueries": {
        "A": {
          "name": "A",
          "query": "max by (consumer_name, stream_name) (nats_consumer_num_pending)",
          "disabled": false
        }
      },
      "unit": ""
    },
    "op": "1",
    "target": 100,
    "matchType": "1",
    "selectedQueryName": "A"
  },
  "labels": {
    "severity": "warning",
    "component": "nats"
  },
  "annotations": {
    "summary": "NATS consumer lag above warn threshold",
    "description": "Consumer {{$labels.consumer_name}} on stream {{$labels.stream_name}} has {{$value}} pending messages (> 100 for 5m)."
  }
}
